{
  "updated": "2026-04-13T10:27:27.117446Z",
  "aiInsight": "Based purely on historical SOT data, Manchester City exceeding 5.5 SOT against Luton shows the highest statistical likelihood, averaging 6.7 home SOT versus Luton's 5.1 away SOT conceded. The key match to avoid is Liverpool vs. Arsenal; high-stakes contests frequently lead to uncharacteristically conservative SOT numbers due to tactical caution. Overall, my confidence in today's SOT card is low, reflecting several fixtures with uncertain tactical approaches and volatile player availability.",
  "resultsSummary": "",
  "hitRate": null,
  "historySummary": {},
  "clvSummary": {},
  "matches": []
}